Workbook

Sheet README
A1: Na-ion EV TEA model (Julian Chitu, NA EV TEM project): transcribed tables
A3: Source | B3: Values hand-copied from the screenshots in 'NaEv Julian Chitu 1.pdf'. Julian's original .xlsx was not available.
A4: Purpose | B4: Working copy of Julian's model, rebuilt with live formulas, as a starting point for the ENGG 192 electrolyte TEA.
A6: Colour key
A7: Blue text | B7: Hard-coded input taken from Julian's slides. Change these.
A8: Black text | B8: Formula. Do not overwrite.
A9: Green text | B9: Link to another sheet.
A10: Yellow fill | B10: Key assumption worth revisiting for the Na-ion electrolyte study.
A11: Pink fill | B11: Mass-balance check (should be 0).
A12: 'Julian's value' columns | B12: Numbers exactly as shown on his slides, kept side by side so you can see where the rebuilt formulas differ.
A14: Sheets
A15: Inputs | B15: Plant basis: pack size, production volume, energy density, losses.
A16: PFD | B16: Process flow mass balance, flows 1–10 with checks.
A17: CapEx | B17: CapEx/GWh, total CapEx, category and equipment breakdowns.
A18: OpEx | B18: Bottom-up material costs and total OpEx.
A19: Cash Flow & Sens | B19: Revenue, annualized CapEx, profit, ±20% sensitivity.
A20: ANL Reference | B20: Argonne BatPaC 2024 pack cost breakdown and material price table used by Julian.
A21: Li Comparison | B21: Julian's qualitative Li vs. Na table.
A22: Model Issues | B22: Inconsistencies found in the original model, and what to change for the electrolyte study.

Sheet Inputs
A1: Inputs: plant basis
A2: From Julian's 'TEM: Inputs' slide
A3: Parameter | B3: Value | C3: Unit | D3: Source / note
A4: Cell energy density | B4: 175 | C4: Wh/kg | D4: https://www.catl.com/en/news/6401.html
A5: Range | B5: 500 | C5: km | D5: Not used downstream
A6: Cycle life | B6: 10000 | C6: cycles | D6: Not used downstream
A7: Batteries per year | B7: 100000 | C7: packs/yr | D7: Scale slide: comparable to UK plant sized for 100k EVs
A8: Useable capacity | B8: 75 | C8: kWh | D8: https://ev-database.org/car/2188/Tesla-Model-3-Performance
A9: Nominal capacity | B9: 78.1 | C9: kWh | D9: Tesla Model 3. Inputs slide shows 78; CapEx slide shows 78.10
A10: Scrap / failures (Inputs slide) | B10: 0 | C10: fraction | D10: https://www.mdpi.com/2075-4701/10/8/1107. Conflicts with the 10% used in the PFD
A12: Calculated
A13: Total annual production | B13: =B9*B7/1000000 -> 7.81 | C13: GWh/yr | D13: Julian: 7.81
A14: Cell mass per battery | B14: =B9*1000/B4 -> 446.28571 | C14: kg/pack | D14: Julian: 446
A15: Annual cell mass | B15: =B14*B7 -> 44628571 | C15: kg/yr | D15: Julian: 44,628,571
A16: Housing + BMS share of mass | B16: 0.2 | C16: fraction | D16: https://pubs.rsc.org/en/content/articlelanding/2016/ee/c6ee00640j
A17: Housing + BMS mass | B17: =B15*B16 -> 8925714.3 | C17: kg/yr | D17: Julian: 8,925,714
A19: Process losses (as used in PFD)
A20: Loss at cell testing | B20: 0.05 | C20: fraction of raw material | D20: PFD: '10% failure for process, split 5% cell testing'
A21: Loss at QA/QC | B21: 0.05 | C21: fraction of raw material | D21: PFD: '5% QA/QC'
A22: Annual raw material required | B22: =B15/(1-B20-B21) -> 49587302 | C22: kg/yr | D22: Julian: 49,587,302
A23: Annual losses | B23: =B22-B15 -> 4958730.2 | C23: kg/yr | D23: Julian: 4,958,730

Sheet PFD
A1: PFD and mass flow balance
A2: Electrode prep → Cell assembly → Cell testing → Module assembly → QA/QC → 100k batteries out
A4: Component | B4: Mass % of raw | C4: Description | D4: Input mass (kg/yr) | E4: Julian's value
A5: Electrolyte | B5: 0.14 | C5: Na salts in ethylene or propylene carbonate | D5: =B5*Inputs!$B$22 -> 6942222.2 | E5: 6942222
A6: Cathode | B6: 0.3 | C6: Prussian White, Na2Fe[Fe(CN)6] | D6: =B6*Inputs!$B$22 -> 14876190 | E6: 14876190
A7: Anode | B7: 0.2 | C7: Hard carbon | D7: =B7*Inputs!$B$22 -> 9917460.3 | E7: 9917460
A8: Housing / casing | B8: 0.23 | D8: =B8*Inputs!$B$22 -> 11405079 | E8: 11404080 | F8: Slide shows 11,404,080 kg; 23% of raw gives 11,405,079 (≈1,000 kg typo, source of the −1 check)
A9: Other | B9: 0.13 | C9: Split below | D9: =B9*Inputs!$B$22 -> 6446349.2 | E9: 6446349
A10: Total | B10: =SUM(B5:B9) -> 1 | D10: =SUM(D5:D9) -> 49587302 | E10: 49587302
A12: 'Other' split | B12: Share of raw | C12: Enters at | D12: Mass (kg/yr) | E12: Julian's value
A13: Binders & conductive additives | B13: 0.04 | C13: Electrode prep | D13: =B13*Inputs!$B$22 -> 1983492.1 | E13: 1983492
A14: Separator membrane | B14: 0.03 | C14: Cell assembly | D14: =B14*Inputs!$B$22 -> 1487619 | E14: 1487619
A15: BMS, wiring, foam, mech. supports | B15: 0.06 | C15: Module assembly | D15: =B15*Inputs!$B$22 -> 2975238.1 | E15: 2976238
A16: Total (must equal 'Other' above) | B16: =SUM(B13:B15) -> 0.13 | D16: =SUM(D13:D15) -> 6446349.2 | F16: =B16-B9 -> 0 | G16: ← check (0)
A18: Flow # | B18: Description | C18: Formula | D18: Mass (kg/yr) | E18: Julian's value
A19: 1 | B19: Electrode materials in (cathode + anode + binders/conductive) | C19: D6+D7+D13 | D19: =D6+D7+D13 -> 26777143 | E19: 26777142
A20: 2 | B20: Electrodes out of prep | C20: D19 | D20: =D19 -> 26777143 | E20: 26777142
A21: 3 | B21: Cell assembly inputs (electrolyte + separator + housing) | C21: D5+D14+D8 | D21: =D5+D14+D8 -> 19834921 | E21: 19833921
A22: 4 | B22: Cells out of assembly | C22: D20+D21 | D22: =D20+D21 -> 46612063 | E22: 46611064
A23: 5 | B23: Cell testing losses | C23: Inputs!B22*Inputs!B20 | D23: =Inputs!B22*Inputs!B20 -> 2479365.1 | E23: 2479365
A24: 6 | B24: Cells passing test | C24: D22-D23 | D24: =D22-D23 -> 44132698 | E24: 44131699
A25: 7 | B25: Module inputs (BMS, wiring, foam, supports) | C25: D15 | D25: =D15 -> 2975238.1 | E25: 2976238
A26: 8 | B26: Modules out of assembly | C26: D24+D25 | D26: =D24+D25 -> 47107937 | E26: 47107937
A27: 9 | B27: QA/QC losses | C27: Inputs!B22*Inputs!B21 | D27: =Inputs!B22*Inputs!B21 -> 2479365.1 | E27: 2479365
A28: 10 | B28: Batteries out (100k packs) | C28: D26-D27 | D28: =D26-D27 -> 44628571 | E28: 44628572
A30: Check | B30: Rule | D30: Difference (kg) | E30: Julian's
A31: Check | B31: 1 = 2 | D31: =D19-D20 -> 0 | E31: 0
A32: Check | B32: 2 + 3 = 4 | D32: =D20+D21-D22 -> 0 | E32: -1
A33: Check | B33: 4 = 5 + 6 | D33: =D22-D23-D24 -> 0 | E33: 0
A34: Check | B34: 6 + 7 = 8 | D34: =D24+D25-D26 -> 0 | E34: 0
A35: Check | B35: 8 = 9 + 10 | D35: =D26-D27-D28 -> 0 | E35: 0
A36: Check | B36: Flow 10 = annual cell mass | D36: =D28-Inputs!B15 -> 0
A37: Check | B37: Inputs = outputs + losses | D37: =D10-D28-D23-D27 -> 0

Sheet CapEx
A1: Capital costs
A2: From Julian's 'TEM: Capital Costs' slide
A3: Parameter | B3: Value | C3: Unit | D3: Source / note
A4: Plant capacity | B4: =Inputs!B13 -> 7.81 | C4: GWh/yr
A5: CapEx per GWh (from exponential fit) | B5: 58.72 | C5: M$/GWh | D5: Read at 7.81 GWh from Julian's exponential fit to KTH capstone scaling data: https://kth.diva-portal.org/smash/get/diva2:1789574/FULLTEXT01.pdf
A6: Total CapEx | B6: =B4*B5 -> 458.6032 | C6: M$ | D6: Julian: 458.02 in cash flow sheet (used 7.80 GWh); 458.6 in breakdown table
A8: Fit data points (approx., read off chart)
A9: Plant capacity (GWh) | B9: CapEx (M$/GWh)
A10: 1 | B10: 90 | D10: Values estimated visually from the chart; fit coefficients were not shown
A11: 10 | B11: 53
A12: 35 | B12: 38
A14: Secondary check
A15: This model at 50 GWh/yr | B15: =B5*50 -> 2936 | C15: M$
A16: Argonne 2024 at 50 GWh/yr | B16: 3433 | C16: M$ | D16: https://www.anl.gov/sites/www/files/2024-11/GPRA2024_06Nov2024.pdf
A17: Ratio (model / Argonne) | B17: =B15/B16 -> 0.85522866
A19: CapEx category | B19: % of total | C19: M$ | D19: Julian's M$
A20: Manufacturing equipment | B20: 0.7 | C20: =B20*$B$6 -> 321.02224 | D20: 321
A21: Facility construction | B21: 0.12 | C21: =B21*$B$6 -> 55.032384 | D21: 55
A22: Engineering & installation | B22: 0.07 | C22: =B22*$B$6 -> 32.102224 | D22: 32.1
A23: Site development & permitting | B23: 0.03 | C23: =B23*$B$6 -> 13.758096 | D23: 13.8
A24: Initial inventory & testing | B24: 0.03 | C24: =B24*$B$6 -> 13.758096 | D24: 13.8
A25: Contingency & overhead | B25: 0.05 | C25: =B25*$B$6 -> 22.93016 | D25: 22.9
A26: Total | B26: =SUM(B20:B25) -> 1 | C26: =SUM(C20:C25) -> 458.6032 | D26: 458.6
A28: Equipment subcategory | B28: % of equipment | C28: M$ | D28: Julian's M$
A29: Electrode production | B29: 0.35 | C29: =B29*$C$20 -> 112.35778 | D29: 112.4
A30: Cell assembly | B30: 0.25 | C30: =B30*$C$20 -> 80.25556 | D30: 80.3
A31: Formation & aging | B31: 0.15 | C31: =B31*$C$20 -> 48.153336 | D31: 48.2
A32: Testing & sorting | B32: 0.1 | C32: =B32*$C$20 -> 32.102224 | D32: 32.1
A33: Material handling & automation | B33: 0.1 | C33: =B33*$C$20 -> 32.102224 | D33: 32.1
A34: Environmental systems (HVAC, dry room) | B34: 0.05 | C34: =B34*$C$20 -> 16.051112 | D34: 16.1 | E34: Dry room / H₂S handling for solid electrolytes would raise this line
A35: Total | B35: =SUM(B29:B34) -> 1 | C35: =SUM(C29:C34) -> 321.02224 | D35: 321

Sheet OpEx
A1: Operating costs
A2: From Julian's 'TEM: Operating Costs' slide. Prices from Argonne BatPaC 2024 (Li-ion materials)
A3: Parameter | B3: Value | C3: Unit | D3: Note
A4: Annual raw material | B4: =Inputs!B22 -> 49587302 | C4: kg/yr
A5: Electrolyte density | B5: 1.2 | C5: kg/L | D5: Not stated by Julian; 1.2 kg/L reproduces his electrolyte cost exactly
A6: Materials + purchased items + BMS share of total cost | B6: 0.77 | C6: fraction | D6: Julian's 'Combined Mat/PI/BMS'. See ANL Reference for what the 2024 table gives
A8: Component | B8: Mass % | C8: Mass (kg/yr) | D8: Unit price | E8: Unit | F8: Cost ($/yr) | G8: Julian's cost ($) | H8: Price source / note
A9: Electrolyte | B9: 0.14 | C9: =B9*$B$4 -> 6942222.2 | D9: 14 | E9: $/L | F9: =C9/$B$5*D9 -> 80992593 | G9: 80992590 | H9: ANL 2024 electrolyte $/L (Li-ion LiPF6/carbonate)
A10: Cathode (Prussian White) | B10: 0.3 | C10: =B10*$B$4 -> 14876190 | D10: 22 | E10: $/kg | F10: =C10*D10 -> 3.2727619e+08 | G10: 327276202 | H10: ANL 2024 NMC811 price, not Prussian White
A11: Anode (hard carbon) | B11: 0.2 | C11: =B11*$B$4 -> 9917460.3 | D11: 9.5 | E11: $/kg | F11: =C11*D11 -> 94215873 | G11: 94215870 | H11: ANL 2024 graphite price, not hard carbon
A12: Housing | B12: 0.23 | C12: =B12*$B$4 -> 11405079 | D12: 4 | E12: $/kg | F12: =C12*D12 -> 45620317 | G12: 45616320
A13: Separator | B13: 0.03 | C13: =B13*$B$4 -> 1487619 | D13: 1 | E13: $/m² (applied per kg) | F13: =C13*D13 -> 1487619 | G13: 1484619 | H13: Unit mismatch: $/m² price multiplied by kg
A14: Binders | B14: 0.02 | C14: =B14*$B$4 -> 991746.03 | D14: 15 | E14: $/kg | F14: =C14*D14 -> 14876190 | G14: 14850000 | H14: ANL positive binder
A15: Conductive carbon | B15: 0.015 | C15: =B15*$B$4 -> 743809.52 | D15: 10 | E15: $/kg | F15: =C15*D15 -> 7438095.2 | G15: 7438100
A16: Collector foil | B16: 0.065 | C16: =B16*$B$4 -> 3223174.6 | D16: 1 | E16: $/kg | F16: =C16*D16 -> 3223174.6 | G16: 3222349 | H16: ANL gives $/m² (Al 0.40, Cu 1.20)
A17: Total materials | B17: =SUM(B9:B16) -> 1 | C17: =SUM(C9:C16) -> 49587302 | F17: =SUM(F9:F16) -> 5.7513005e+08 | G17: 575096050
A18: Electrolyte share of material cost | F18: =F9/F17 -> 0.14082483
A20: Summary | B20: M$/yr | G20: Julian's
A21: Material cost | B21: =F17/1000000 -> 575.13005 | G21: 575.1
A22: Total OpEx (= materials / share) | B22: =B21/B6 -> 746.92215 | G22: 746.85
A23: Non-material OpEx (labor, energy, depreciation, overhead) | B23: =B22-B21 -> 171.79209
A24: OpEx per kWh | B24: =B22*1000000/(Inputs!B13*1000000) -> 95.636638 | C24: $/kWh
A25: Electrolyte cost per kWh | B25: =F9/(Inputs!B13*1000000) -> 10.37037 | C25: $/kWh

Sheet Cash Flow & Sens
A1: Total costs, profit and sensitivities
A2: From Julian's 'TEM: Total Costs and Sensitivities' slide
A3: Parameter | B3: Value | C3: Unit | D3: Julian's | E3: Note
A4: CapEx | B4: =CapEx!B6 -> 458.6032 | C4: M$ | D4: 458.02
A5: Total OpEx | B5: =OpEx!B22 -> 746.92215 | C5: M$/yr | D5: 746.85
A6: Pack cost, no margin | B6: ='ANL Reference'!C16-'ANL Reference'!C14 -> 9849 | C6: $/pack | D6: 9849 | E6: ANL 2024 total pack cost minus profits (Li-ion NMC pack)
A7: Margin | B7: 0.1 | C7: fraction | D7: 0.1
A8: Discount rate | B8: 0.07 | C8: fraction | D8: 0.07
A9: Recovery period | B9: 3 | C9: yr | D9: 3 | E9: Short vs. typical 10–15 yr equipment life
A10: Annuity factor | B10: =(1-(1+B8)^(-B9))/B8 -> 2.624316 | D10: 2.62
A11: EAC (annualized CapEx) | B11: =B4/B10 -> 174.75151 | C11: M$/yr | D11: 174.53
A12: Sale price per pack | B12: =B6*(1+B7) -> 10833.9 | C12: $/pack
A13: Total yearly sales | B13: =B12*Inputs!B7/1000000 -> 1083.39 | C13: M$/yr | D13: 1083.39
A14: Net profit, years 1–3 | B14: =B13-B5-B11 -> 161.71634 | C14: M$/yr | D14: 162.01
A15: Net profit after recovery | B15: =B13-B5 -> 336.46785 | C15: M$/yr | D15: 336.54
A17: Sensitivity: change in profit, years 1–3 (M$/yr), one parameter at a time
A18: Swing | B18: 0.2
A19: Parameter | B19: Base (M$/yr) | C19: Δ profit at −swing | D19: Δ profit at +swing | E19: Julian's |Δ| (approx.)
A20: Cathode cost | B20: =OpEx!F10/1000000 -> 327.27619 | C20: =1*$B$18*B20 -> 65.455238 | D20: =-1*$B$18*B20 -> -65.455238 | E20: 65
A21: CapEx (EAC) | B21: =B11 -> 174.75151 | C21: =1*$B$18*B21 -> 34.950303 | D21: =-1*$B$18*B21 -> -34.950303 | E21: 35
A22: OpEx (non-material) | B22: =OpEx!B23 -> 171.79209 | C22: =1*$B$18*B22 -> 34.358419 | D22: =-1*$B$18*B22 -> -34.358419 | E22: 35
A23: Sales price (margin) | B23: =B6*B7*Inputs!B7/1000000 -> 98.49 | C23: =-$B$18*B23 -> -19.698 | D23: =$B$18*B23 -> 19.698 | E23: 21
A24: Anode cost | B24: =OpEx!F11/1000000 -> 94.215873 | C24: =1*$B$18*B24 -> 18.843175 | D24: =-1*$B$18*B24 -> -18.843175 | E24: 19
A25: Electrolyte cost | B25: =OpEx!F9/1000000 -> 80.992593 | C25: =1*$B$18*B25 -> 16.198519 | D25: =-1*$B$18*B25 -> -16.198519 | E25: 16
A27: Cost items: +20% cost lowers profit. Julian's tornado labels cost increases as the green (positive) bar, which looks reversed.

Sheet ANL Reference
A1: Argonne reference tables (as used by Julian)
A2: Source: https://www.anl.gov/sites/www/files/2024-11/GPRA2024_06Nov2024.pdf (BatPaC, Li-ion NMC811/graphite pack)
A3: Pack cost breakdown ($/pack) | B3: 2023 | C3: 2024
A4: Materials | B4: 6739 | C4: 6084
A5: Purchased items | B5: 1097 | C5: 1097
A6: BMS | B6: 403 | C6: 403
A7: Energy | B7: 158 | C7: 158
A8: Depreciation | B8: 644 | C8: 644
A9: Labor | B9: 186 | C9: 186
A10: Other variable overhead | B10: 250 | C10: 250
A11: Other GSA | B11: 175 | C11: 175
A12: R&D | B12: 225 | C12: 225
A13: Financing | B13: 79 | C13: 78
A14: Profits | B14: 528 | C14: 522
A15: Warranty | B15: 587 | C15: 550
A16: Total pack cost (as published) | B16: 11071 | C16: 10371
A17: Sum of lines (check) | B17: =SUM(B4:B15) -> 11071 | C17: =SUM(C4:C15) -> 10372
A18: Materials + purchased items + BMS share | B18: =SUM(B4:B6)/B16 -> 0.74419655 | C18: =SUM(C4:C6)/C16 -> 0.73126989 | D18: Compare with the 77% Julian used on the OpEx sheet
A20: Material price assumptions | B20: 2019 | C20: 2020 | D20: 2021 | E20: 2022 | F20: 2023 | G20: 2024
A21: Cathode active material (CAM) | B21: NMC622 | C21: NMC811 | D21: NMC811 | E21: NMC811 | F21: NMC811 | G21: NMC811
A22: Cathode active material, $/kg | B22: 21 | C22: 22 | D22: 22.8 | E22: 26 | F22: 26 | G22: 22
A23: Graphite, $/kg | B23: 14 | C23: 14 | D23: 11 | E23: 10 | F23: 10 | G23: 9.5
A24: Electrolyte, $/L | B24: 15 | C24: 15 | D24: 15 | E24: 15 | F24: 15 | G24: 14
A25: Separator, $/m² | B25: 1.1 | C25: 1 | D25: 1 | E25: 1 | F25: 1 | G25: 1
A26: Aluminum current collector, $/m² | B26: 0.4 | C26: 0.4 | D26: 0.4 | E26: 0.4 | F26: 0.4 | G26: 0.4
A27: Copper current collector, $/m² | B27: 1.2 | C27: 1.2 | D27: 1.2 | E27: 1.2 | F27: 1.2 | G27: 1.2
A28: Positive binder, $/kg | B28: 10 | C28: 10 | D28: 10 | E28: 15 | F28: 15 | G28: 15
A29: NMP, $/kg | B29: 3.1 | C29: 3.1 | D29: 3.1 | E29: 3.1 | F29: 3.1 | G29: 3.1
A31: All prices are for Li-ion materials. Na-ion equivalents (Prussian White, hard carbon, NaPF₆ electrolyte) need their own sources.

Sheet Li Comparison
A1: Comparison with Li (qualitative, from Julian's slide)
A3: Category | B3: Lithium-ion | C3: Sodium-ion
A4: Energy density | B4: High (200–250 Wh/kg) | C4: Moderate (100–175 Wh/kg)
A5: Material abundance | B5: Limited | C5: Abundant
A6: Raw material cost | B6: High | C6: Low
A7: Thermal stability | B7: Moderate | C7: High
A8: Charging compatibility | B8: Mature and well-supported | C8: Developing, may need adaptation
A9: Market maturity | B9: Global | C9: Emerging, early commercialization phase
A10: Environmental impact | B10: Moderate | C10: Low (claim, not quantified — your LCA tests this)
A11: OEM adoption | B11: High (almost all current EVs) | C11: Low (R&D and China)

Sheet Model Issues
A1: Issues in the original model and changes for the ENGG 192 electrolyte TEA
A3: # | B3: Where | C3: Issue | D3: Effect | E3: Suggested change
A4: 1 | B4: OpEx | C4: Cathode priced at NMC811 ($22/kg), anode at graphite ($9.50/kg) | D4: Cathode dominates cost; 'cathode drives profitability' is partly an artifact | E4: Source Prussian White and hard carbon prices
A5: 2 | B5: Cash Flow | C5: Revenue = Li-ion pack cost + 10% margin | D5: Profit is circular; says little about Na-ion competitiveness | E5: Report levelized cost ($/kWh) or minimum selling price instead of profit
A6: 3 | B6: OpEx | C6: Total OpEx scaled from materials with a Li-ion ratio (77%) | D6: Non-material costs are not modeled bottom-up | E6: Build labor, energy, dry room, depreciation lines directly
A7: 4 | B7: Cash Flow | C7: 3-year CapEx recovery | D7: Overstates annualized CapEx in years 1–3; profit jumps after year 3 | E7: Use 10–15 yr plant life and a full NPV or levelized cost
A8: 5 | B8: Inputs vs PFD | C8: Scrap = 0 on Inputs, 10% losses in PFD | D8: Inconsistent basis | E8: One loss parameter per process step, used everywhere
A9: 6 | B9: PFD vs OpEx | C9: 'Other' = binders + separator + BMS in PFD, but binders + conductive + separator + collector foil in OpEx | D9: BMS disappears from costing; collector foil appears | E9: Use one component list across sheets
A10: 7 | B10: OpEx | C10: Separator ($/m²) and collector foil ($/m²) multiplied by kg | D10: Unit error | E10: Convert via areal density (g/m²) or area per kWh
A11: 8 | B11: PFD | C11: Housing typo (11,404,080 vs 11,405,079 kg) | D11: −1 kg mass balance check | E11: Fixed here by using formulas
A12: 9 | B12: Inputs | C12: Cycle life and range not used | D12: No lifetime or $/kWh-cycle metric | E12: For stationary storage, add cycle life to a levelized cost of storage
A13: 10 | B13: Sensitivity | C13: One-at-a-time ±20% only | D13: No interactions or uncertainty ranges | E13: Add scenario ranges or Monte Carlo on TRL-sensitive parameters
A14: 11 | B14: Scope (ENGG 192) | C14: Pack-level EV plant | D14: Electrolyte is 14% of mass and one line of cost | E14: Move the boundary to electrolyte production + cell integration; keep this liquid cell as the NaPF₆ baseline
